.bumpversion.cfg
.gitignore
CHANGELOG.md
MANIFEST.in
README.md
justfile
requirements-dev.txt
requirements-flake8.txt
requirements.txt
setup.py
template-version.txt
tox.ini
.githooks/prepare-commit-msg
src/fhs_anki_ctrl/__init__.py
src/fhs_anki_ctrl/__version__.py
src/fhs_anki_ctrl/anki_class.py
src/fhs_anki_ctrl/cli.py
src/fhs_anki_ctrl/config.py
src/fhs_anki_ctrl/fhs_anki_ctrl.py
src/fhs_anki_ctrl/qa_file.py
src/fhs_anki_ctrl.egg-info/PKG-INFO
src/fhs_anki_ctrl.egg-info/SOURCES.txt
src/fhs_anki_ctrl.egg-info/dependency_links.txt
src/fhs_anki_ctrl.egg-info/entry_points.txt
src/fhs_anki_ctrl.egg-info/requires.txt
src/fhs_anki_ctrl.egg-info/top_level.txt
tests/test_qafile.py
tests/test_sample.py
tests/data/qa_file.txt