Metadata-Version: 2.1
Name: fhs-anki-ctrl
Version: 0.9.0
Summary: control local anki-qt
Home-page: https://github.com/foxhunt72/fhs-anki-ctrl
Author: Richard de Vos
Author-email: rdevos72@gmail.com
License: MIT license
Classifier: Development Status :: 4 - Beta
Classifier: Programming Language :: Python
Classifier: Programming Language :: Python :: 3
Classifier: Programming Language :: Python :: 3.7
Classifier: Programming Language :: Python :: 3.8
Classifier: Programming Language :: Python :: 3.9
Classifier: Programming Language :: Python :: 3.10
Classifier: Programming Language :: Python :: 3.11
